{
  "$schema": "http://json.schemastore.org/sarif-1.0.0",
  "version": "1.0.0",
  "runs": [
    {
      "tool": {
        "name": "Compilador de Microsoft (R) Visual C#",
        "version": "3.11.0.0",
        "fileVersion": "3.11.0-4.22108.8 (d9bef045)",
        "semanticVersion": "3.11.0",
        "language": "es-MX"
      },
      "results": [
        {
          "ruleId": "S1118",
          "level": "warning",
          "message": "Add a 'protected' constructor or the 'static' keyword to the class declaration.",
          "locations": [
            {
              "resultFile": {
                "uri": "file:///D:/Proyecto/SistemaDiagnostico/SistemaDiagnostico.Negocio/EnfermedadPosibleNegocio.cs",
                "region": {
                  "startLine": 12,
                  "startColumn": 18,
                  "endLine": 12,
                  "endColumn": 42
                }
              }
            }
          ],
          "properties": {
            "warningLevel": 1
          }
        },
        {
          "ruleId": "S1118",
          "level": "warning",
          "message": "Add a 'protected' constructor or the 'static' keyword to the class declaration.",
          "locations": [
            {
              "resultFile": {
                "uri": "file:///D:/Proyecto/SistemaDiagnostico/SistemaDiagnostico.Negocio/DetalleDiagnosticoNegocio.cs",
                "region": {
                  "startLine": 13,
                  "startColumn": 18,
                  "endLine": 13,
                  "endColumn": 43
                }
              }
            }
          ],
          "properties": {
            "warningLevel": 1
          }
        },
        {
          "ruleId": "S1118",
          "level": "warning",
          "message": "Add a 'protected' constructor or the 'static' keyword to the class declaration.",
          "locations": [
            {
              "resultFile": {
                "uri": "file:///D:/Proyecto/SistemaDiagnostico/SistemaDiagnostico.Negocio/DiagnosticoNegocio.cs",
                "region": {
                  "startLine": 13,
                  "startColumn": 18,
                  "endLine": 13,
                  "endColumn": 36
                }
              }
            }
          ],
          "properties": {
            "warningLevel": 1
          }
        },
        {
          "ruleId": "S1118",
          "level": "warning",
          "message": "Add a 'protected' constructor or the 'static' keyword to the class declaration.",
          "locations": [
            {
              "resultFile": {
                "uri": "file:///D:/Proyecto/SistemaDiagnostico/SistemaDiagnostico.Negocio/EmpleadoNegocio.cs",
                "region": {
                  "startLine": 12,
                  "startColumn": 18,
                  "endLine": 12,
                  "endColumn": 33
                }
              }
            }
          ],
          "properties": {
            "warningLevel": 1
          }
        },
        {
          "ruleId": "S1118",
          "level": "warning",
          "message": "Add a 'protected' constructor or the 'static' keyword to the class declaration.",
          "locations": [
            {
              "resultFile": {
                "uri": "file:///D:/Proyecto/SistemaDiagnostico/SistemaDiagnostico.Negocio/PacienteNegocio.cs",
                "region": {
                  "startLine": 13,
                  "startColumn": 18,
                  "endLine": 13,
                  "endColumn": 33
                }
              }
            }
          ],
          "properties": {
            "warningLevel": 1
          }
        },
        {
          "ruleId": "S1118",
          "level": "warning",
          "message": "Add a 'protected' constructor or the 'static' keyword to the class declaration.",
          "locations": [
            {
              "resultFile": {
                "uri": "file:///D:/Proyecto/SistemaDiagnostico/SistemaDiagnostico.Negocio/UsuarioNegocio.cs",
                "region": {
                  "startLine": 12,
                  "startColumn": 18,
                  "endLine": 12,
                  "endColumn": 32
                }
              }
            }
          ],
          "properties": {
            "warningLevel": 1
          }
        }
      ],
      "rules": {
        "S1118": {
          "id": "S1118",
          "shortDescription": "Utility classes should not have public constructors",
          "fullDescription": "Utility classes, which are collections of static members, are not meant to be instantiated.",
          "defaultLevel": "warning",
          "helpUri": "https://rules.sonarsource.com/csharp/RSPEC-1118",
          "properties": {
            "category": "Major Code Smell",
            "isEnabledByDefault": true,
            "tags": [
              "C#",
              "SonarWay",
              "MainSourceScope",
              "TestSourceScope"
            ]
          }
        }
      }
    }
  ]
}